{"category_code":"games_video","founded_year":2006,"name":"Curse","number_of_employees":58,"position":{"type":"Point","coordinates":[-122.399972,37.787092]}}
{"category_code":"web","founded_year":2008,"name":"Lolapps","number_of_employees":65,"position":{"type":"Point","coordinates":[-122.3999719,37.7870923]}}
{"category_code":"games_video","founded_year":2003,"name":"hi5","number_of_employees":100,"position":{"type":"Point","coordinates":[-122.400558,37.788668]}}
{"category_code":"web","founded_year":2007,"name":"Huddler","number_of_employees":52,"position":{"type":"Point","coordinates":[-122.4013624,37.7893215]}}
{"category_code":"enterprise","founded_year":2007,"name":"Twilio","number_of_employees":100,"position":{"type":"Point","coordinates":[-122.4006831,37.7898499]}}
{"category_code":"software","founded_year":2007,"name":"Lyft","number_of_employees":180,"position":{"type":"Point","coordinates":[-122.4007846,37.7899027]}}
{"category_code":"mobile","founded_year":2008,"name":"5th Finger","number_of_employees":50,"position":{"type":"Point","coordinates":[-122.4021988,37.7900992]}}
{"category_code":"enterprise","founded_year":2004,"name":"Birst","number_of_employees":150,"position":{"type":"Point","coordinates":[-122.404113,37.789471]}}
{"category_code":"web","founded_year":2007,"name":"Yola","number_of_employees":70,"position":{"type":"Point","coordinates":[-122.3954751,37.7911148]}}
{"category_code":"web","founded_year":2004,"name":"BitTorrent","number_of_employees":80,"position":{"type":"Point","coordinates":[-122.394668,37.790998]}}
{"category_code":"web","founded_year":2004,"name":"Double Fusion","number_of_employees":80,"position":{"type":"Point","coordinates":[-122.3927145,37.7887135]}}
{"category_code":"ecommerce","founded_year":2005,"name":"Blurb","number_of_employees":150,"position":{"type":"Point","coordinates":[-122.40414,37.792968]}}
{"category_code":"ecommerce","founded_year":2006,"name":"RichRelevance","number_of_employees":250,"position":{"type":"Point","coordinates":[-122.4000965,37.7938969]}}
{"category_code":"analytics","founded_year":2007,"name":"Kontagent","number_of_employees":80,"position":{"type":"Point","coordinates":[-122.4020593,37.7797255]}}
{"category_code":"software","founded_year":2007,"name":"Dropbox","number_of_employees":350,"position":{"type":"Point","coordinates":[-122.4084994,37.7909427]}}
{"category_code":"games_video","founded_year":2008,"name":"Crunchyroll","number_of_employees":50,"position":{"type":"Point","coordinates":[-122.393229,37.781265]}}
{"category_code":"software","founded_year":2003,"name":"Splunk","number_of_employees":500,"position":{"type":"Point","coordinates":[-122.390945,37.78274]}}
{"category_code":"web","founded_year":2006,"name":"Weebly","number_of_employees":70,"position":{"type":"Point","coordinates":[-122.400729,37.795555]}}